setup.py
appletweets.egg-info/PKG-INFO
appletweets.egg-info/SOURCES.txt
appletweets.egg-info/dependency_links.txt
appletweets.egg-info/top_level.txt
extra/__init__.py
extra/divide.py
extra/multiply.py