Metadata-Version: 1.1
Name: appletweets
Version: 0.0.1
Summary: My first Python package
Home-page: UNKNOWN
Author: Naramula venkatesh
Author-email: naramulavenkatesh@gmail.com
License: UNKNOWN
Keywords: python,first package
Platform: UNKNOWN
Classifier: Development Status :: 3 - Alpha
Classifier: Intended Audience :: Education
Classifier: Programming Language :: Python :: 2
Classifier: Programming Language :: Python :: 3
